COPYING
README.md
setup.py
pubcontrol.egg-info/PKG-INFO
pubcontrol.egg-info/SOURCES.txt
pubcontrol.egg-info/dependency_links.txt
pubcontrol.egg-info/requires.txt
pubcontrol.egg-info/top_level.txt
src/__init__.py
src/format.py
src/item.py
src/pcccbhandler.py
src/pubcontrol.py
src/pubcontrolclient.py
src/pubsubmonitor.py
src/utilities.py
src/zmqpubcontrolclient.py
src/zmqpubcontroller.py