Metadata-Version: 2.1
Name: pubcontrol
Version: 3.3.0
Summary: EPCP library
Home-page: https://github.com/fanout/pypubcontrol
Author: Justin Karneges
Author-email: justin@fanout.io
License: MIT
Platform: UNKNOWN
Classifier: Topic :: Utilities
Classifier: License :: OSI Approved :: MIT License
License-File: COPYING
